jquantstats/__init__.py
jquantstats/_data.py
jquantstats/_plots.py
jquantstats/_reports.py
jquantstats/_stats.py
jquantstats/api.py
jquantstats-0.0.32.dist-info/METADATA
jquantstats-0.0.32.dist-info/WHEEL
jquantstats-0.0.32.dist-info/licenses/LICENSE
jquantstats-0.0.32.dist-info/RECORD
