Metadata-Version: 2.4
Name: jquantstats
Version: 0.0.32
Summary: Analytics for quants
Project-URL: repository, https://github.com/tschm/jquantstats
Author-email: tschm <thomas.schmelzer@gmail.com>
License-File: LICENSE
Requires-Python: >=3.11
Requires-Dist: numpy>=2.0.0
Requires-Dist: pandas>=2.2.3
Requires-Dist: plotly>=6.0.0
Requires-Dist: polars>=1.18.0
Requires-Dist: pyarrow>=22.0.0
Requires-Dist: scipy>=1.14.1
Provides-Extra: dev
Requires-Dist: ipython==9.7.0; extra == 'dev'
Requires-Dist: marimo>=0.13.15; extra == 'dev'
Requires-Dist: pytest-cov==7.0.0; extra == 'dev'
Requires-Dist: pytest==9.0.0; extra == 'dev'
Requires-Dist: quantstats==0.0.77; extra == 'dev'
Requires-Dist: yfinance==0.2.66; extra == 'dev'
Provides-Extra: plot
Requires-Dist: kaleido==1.2.0; extra == 'plot'
